MANIFEST.in
setup.py
ephys_viz_jup/__init__.py
ephys_viz_jup/_version.py
ephys_viz_jup/all_widgets.py
ephys_viz_jup/init.py
ephys_viz_jup.egg-info/PKG-INFO
ephys_viz_jup.egg-info/SOURCES.txt
ephys_viz_jup.egg-info/dependency_links.txt
ephys_viz_jup.egg-info/requires.txt
ephys_viz_jup.egg-info/top_level.txt
ephys_viz_jup/dist/bundle.js
ephys_viz_jup/widgets/__init__.py
ephys_viz_jup/widgets/create_sync.py
ephys_viz_jup/widgets/jupyter.py
ephys_viz_jup/widgets/Accordion/Accordion.py
ephys_viz_jup/widgets/Accordion/__init__.py
ephys_viz_jup/widgets/Autocorrelograms/Autocorrelograms.py
ephys_viz_jup/widgets/Autocorrelograms/__init__.py
ephys_viz_jup/widgets/ElectrodeGeometry/ElectrodeGeometry.py
ephys_viz_jup/widgets/ElectrodeGeometry/__init__.py
ephys_viz_jup/widgets/HBox/HBox.py
ephys_viz_jup/widgets/HBox/__init__.py
ephys_viz_jup/widgets/NWBBrowser/NWBBrowser.py
ephys_viz_jup/widgets/NWBBrowser/__init__.py
ephys_viz_jup/widgets/NWBBrowser/h5_to_dict.py
ephys_viz_jup/widgets/NWBView/NWBView.py
ephys_viz_jup/widgets/NWBView/__init__.py
ephys_viz_jup/widgets/NWBView/h5_to_dict.py
ephys_viz_jup/widgets/PlaceField/PlaceField.py
ephys_viz_jup/widgets/PlaceField/__init__.py
ephys_viz_jup/widgets/SpikeForestAnalysis/SpikeForestAnalysis.py
ephys_viz_jup/widgets/SpikeForestAnalysis/__init__.py
ephys_viz_jup/widgets/Tabs/Tabs.py
ephys_viz_jup/widgets/Tabs/__init__.py
ephys_viz_jup/widgets/TimeseriesView/TimeseriesView.py
ephys_viz_jup/widgets/TimeseriesView/__init__.py
ephys_viz_jup/widgets/VBox/VBox.py
ephys_viz_jup/widgets/VBox/__init__.py
ephys_viz_jup/widgets/pycommon/__init__.py
ephys_viz_jup/widgets/pycommon/nwb_to_dict.py